LICENSE
MANIFEST.in
README.rst
setup.py
matrix_parser/__init__.py
matrix_parser/matrix_parser.py
matrix_parser/matrix_parser_base.py
matrix_parser.egg-info/PKG-INFO
matrix_parser.egg-info/SOURCES.txt
matrix_parser.egg-info/dependency_links.txt
matrix_parser.egg-info/top_level.txt
test/__init__.py
test/context.py
test/test_matrix_parser.py
test/test_matrix_parser_base.py