Metadata-Version: 1.0
Name: matrix-parser
Version: 1.0.2
Summary: A matrix shaped text (e.g csv) parser
Home-page: https://github.com/heliosantos/matrix_parser
Author: Hélio Santos
Author-email: heliosantos99@gmail.com
License: Copyright (c) 2016 Hélio Santos
